alerts_msg/__init__.py
alerts_msg/main.py
alerts_msg/smtp.py
alerts_msg/telegram.py
alerts_msg-0.2.1.dist-info/LICENSE
alerts_msg-0.2.1.dist-info/METADATA
alerts_msg-0.2.1.dist-info/WHEEL
alerts_msg-0.2.1.dist-info/top_level.txt
alerts_msg-0.2.1.dist-info/RECORD
